LICENSE.txt
MANIFEST.in
setup.cfg
setup.py
qtim_tools/__init__.py
qtim_tools.egg-info/PKG-INFO
qtim_tools.egg-info/SOURCES.txt
qtim_tools.egg-info/dependency_links.txt
qtim_tools.egg-info/requires.txt
qtim_tools.egg-info/top_level.txt
qtim_tools/qtim_dce/__init__.py
qtim_tools/qtim_dce/dce_util.py
qtim_tools/qtim_dce/help.py
qtim_tools/qtim_dce/process_dce_file.py
qtim_tools/qtim_dce/tofts_parameter_calculator.py
qtim_tools/qtim_dce/tofts_parametric_mapper.py
qtim_tools/qtim_dce/tofts_worker.py
qtim_tools/qtim_features/GLCM.py
qtim_tools/qtim_features/__init__.py
qtim_tools/qtim_features/extract_features.py
qtim_tools/qtim_features/morphology.py
qtim_tools/qtim_features/phantoms.py
qtim_tools/qtim_features/statistics.py
qtim_tools/qtim_features/test.py
qtim_tools/qtim_learning/__init__.py
qtim_tools/qtim_learning/nn_preprocessing.py
qtim_tools/qtim_pipelines/__init__.py
qtim_tools/qtim_pipelines/process_dce.py
qtim_tools/qtim_preprocessing/__init__.py
qtim_tools/qtim_preprocessing/image.py
qtim_tools/qtim_preprocessing/normalization.py
qtim_tools/qtim_preprocessing/registration.py
qtim_tools/qtim_preprocessing/signal.py
qtim_tools/qtim_utilities/__init__.py
qtim_tools/qtim_utilities/dicom_util.py
qtim_tools/qtim_utilities/file_util.py
qtim_tools/qtim_utilities/format.py
qtim_tools/qtim_utilities/nifti_util.py
qtim_tools/qtim_utilities/nrrd_util.py
qtim_tools/qtim_utilities/scratch_util.py
qtim_tools/qtim_visualization/__init__.py
qtim_tools/test_data/__init__.py
qtim_tools/test_data/load.py
qtim_tools/test_data/test_data_features/MRBrainTumor2-label.nii.gz
qtim_tools/test_data/test_data_features/MRBrainTumor2.nii.gz
qtim_tools/test_data/test_data_features/MRHead-label.nii.gz
qtim_tools/test_data/test_data_features/MRHead.nii.gz
qtim_tools/test_data/test_data_features/MR_Tumor_Shape/MR_BrainTumor_ShapeTest-label.nii.gz
qtim_tools/test_data/test_data_features/MR_Tumor_Shape/MR_BrainTumor_ShapeTest.nii.gz
qtim_tools/test_data/test_data_features/MR_Tumor_Size/MR_BrainTumor_SizeTest-label.nii.gz
qtim_tools/test_data/test_data_features/MR_Tumor_Size/MR_BrainTumor_SizeTest.nii.gz
